sinfonia_tier3/__init__.py
sinfonia_tier3/__main__.py
sinfonia_tier3/cli.py
sinfonia_tier3/cloudlet_deployment.py
sinfonia_tier3/key_cache.py
sinfonia_tier3/local_deployment.py
sinfonia_tier3/netns_helper.py
sinfonia_tier3/openapi/sinfonia_tier2.yaml
sinfonia_tier3/py.typed
sinfonia_tier3/root_helper.py
sinfonia_tier3-0.7.4.dist-info/LICENSE
sinfonia_tier3-0.7.4.dist-info/LICENSES/0BSD.txt
sinfonia_tier3-0.7.4.dist-info/LICENSES/CC-PDDC.txt
sinfonia_tier3-0.7.4.dist-info/LICENSES/MIT.txt
sinfonia_tier3-0.7.4.dist-info/METADATA
sinfonia_tier3-0.7.4.dist-info/WHEEL
sinfonia_tier3-0.7.4.dist-info/entry_points.txt
sinfonia_tier3-0.7.4.dist-info/RECORD
