Metadata-Version: 2.1
Name: sinfonia-tier3
Version: 0.7.4
Summary: Tier 3 component of the Sinfonia system
Home-page: https://github.com/cmusatyalab/sinfonia-tier3
License: MIT
Author: Carnegie Mellon University
Author-email: satya+group@cs.cmu.edu
Requires-Python: >=3.7,<4.0
Classifier: Development Status :: 4 - Beta
Classifier: Environment :: Console
Classifier: Intended Audience :: Developers
Classifier: License :: OSI Approved :: MIT License
Classifier: Programming Language :: Python :: 3
Classifier: Programming Language :: Python :: 3.7
Classifier: Programming Language :: Python :: 3.8
Classifier: Programming Language :: Python :: 3.9
Classifier: Programming Language :: Python :: 3.10
Classifier: Programming Language :: Python :: 3.11
Classifier: Programming Language :: Python :: 3.12
Requires-Dist: attrs (>=22.1.0)
Requires-Dist: importlib-resources (>=5.0,<6.0)
Requires-Dist: openapi-core (>=0.17.2,<0.18.0)
Requires-Dist: pyroute2 (>=0.7.3,<0.8.0)
Requires-Dist: pyyaml (>=6.0,<7.0)
Requires-Dist: requests (>=2.28.1,<3.0.0)
Requires-Dist: typing-extensions (>=4.4.0,<5.0.0)
Requires-Dist: wireguard-tools (>=0.4.1,<0.5.0)
Requires-Dist: wireguard4netns (>=0.1.3,<0.2.0)
Requires-Dist: xdg (>=5.1.1,<6.0.0)
Requires-Dist: yarl (>=1.7.2,<2.0.0)
Project-URL: Repository, https://github.com/cmusatyalab/sinfonia-tier3
